pip_wrapper/__init__.py
pip_wrapper/cli.py
pip_helper-0.1.0.dist-info/LICENSE
pip_helper-0.1.0.dist-info/METADATA
pip_helper-0.1.0.dist-info/WHEEL
pip_helper-0.1.0.dist-info/entry_points.txt
pip_helper-0.1.0.dist-info/top_level.txt
pip_helper-0.1.0.dist-info/RECORD
